{
  "prediction_date": "2026-05-19",
  "config": "JMA_Full+GPS",
  "data_hashes": {
    "usgs": "9cd2f1d19a802ef7",
    "jma": "0696743cf1be8ecb",
    "gps": "3778bc7bf860602f"
  },
  "zones": [
    {
      "zone_id": "Z_15_120",
      "name": "Okinawa",
      "pop_millions": 28,
      "tiers": {
        "T1": {
          "probability": 0.037666,
          "alerts": {
            "0.5pct": false,
            "1.0pct": false,
            "2.0pct": false,
            "5.0pct": false,
            "10.0pct": false
          },
          "validity": {
            "window_days": 2,
            "valid_from": "2026-05-20T00:00:00Z",
            "valid_to": "2026-05-21T23:59:59Z"
          },
          "probability_seismic": 0.037666,
          "gps_reliability": 0.646,
          "boost": 0.0
        },
        "T2": {
          "probability": 0.258042,
          "alerts": {
            "0.5pct": false,
            "1.0pct": false,
            "2.0pct": false,
            "5.0pct": false,
            "10.0pct": false
          },
          "validity": {
            "window_days": 2,
            "valid_from": "2026-05-20T00:00:00Z",
            "valid_to": "2026-05-21T23:59:59Z"
          },
          "probability_seismic": 0.258042,
          "gps_reliability": 0.646,
          "boost": 0.0
        },
        "T3": {
          "probability": 0.333629,
          "alerts": {
            "0.5pct": false,
            "1.0pct": false,
            "2.0pct": false,
            "5.0pct": false,
            "10.0pct": false
          },
          "validity": {
            "window_days": 3,
            "valid_from": "2026-05-20T00:00:00Z",
            "valid_to": "2026-05-22T23:59:59Z"
          },
          "probability_seismic": 0.333629,
          "gps_reliability": 0.646,
          "boost": 0.0
        },
        "T4": {
          "probability": 0.309692,
          "alerts": {
            "0.5pct": false,
            "1.0pct": false,
            "2.0pct": false,
            "5.0pct": false,
            "10.0pct": false
          },
          "validity": {
            "window_days": 3,
            "valid_from": "2026-05-20T00:00:00Z",
            "valid_to": "2026-05-22T23:59:59Z"
          },
          "probability_seismic": 0.309692,
          "gps_reliability": 0.646,
          "boost": 0.0
        }
      }
    },
    {
      "zone_id": "Z_15_145",
      "name": "Z_15_145",
      "pop_millions": 0,
      "tiers": {
        "T1": {
          "probability": 0.037872,
          "alerts": {
            "0.5pct": false,
            "1.0pct": false,
            "2.0pct": false,
            "5.0pct": false,
            "10.0pct": false
          },
          "validity": {
            "window_days": 2,
            "valid_from": "2026-05-20T00:00:00Z",
            "valid_to": "2026-05-21T23:59:59Z"
          },
          "probability_seismic": 0.037872,
          "gps_reliability": 0.25,
          "boost": 0.0
        },
        "T2": {
          "probability": 0.258409,
          "alerts": {
            "0.5pct": false,
            "1.0pct": false,
            "2.0pct": false,
            "5.0pct": false,
            "10.0pct": false
          },
          "validity": {
            "window_days": 2,
            "valid_from": "2026-05-20T00:00:00Z",
            "valid_to": "2026-05-21T23:59:59Z"
          },
          "probability_seismic": 0.258409,
          "gps_reliability": 0.25,
          "boost": -0.0
        },
        "T3": {
          "probability": 0.333897,
          "alerts": {
            "0.5pct": false,
            "1.0pct": false,
            "2.0pct": false,
            "5.0pct": false,
            "10.0pct": false
          },
          "validity": {
            "window_days": 3,
            "valid_from": "2026-05-20T00:00:00Z",
            "valid_to": "2026-05-22T23:59:59Z"
          },
          "probability_seismic": 0.333897,
          "gps_reliability": 0.25,
          "boost": 0.0
        },
        "T4": {
          "probability": 0.310011,
          "alerts": {
            "0.5pct": false,
            "1.0pct": false,
            "2.0pct": false,
            "5.0pct": false,
            "10.0pct": false
          },
          "validity": {
            "window_days": 3,
            "valid_from": "2026-05-20T00:00:00Z",
            "valid_to": "2026-05-22T23:59:59Z"
          },
          "probability_seismic": 0.310011,
          "gps_reliability": 0.25,
          "boost": 0.0
        }
      }
    },
    {
      "zone_id": "Z_20_120",
      "name": "Ryukyu",
      "pop_millions": 8,
      "tiers": {
        "T1": {
          "probability": 0.723575,
          "alerts": {
            "0.5pct": false,
            "1.0pct": false,
            "2.0pct": false,
            "5.0pct": false,
            "10.0pct": false
          },
          "validity": {
            "window_days": 2,
            "valid_from": "2026-05-20T00:00:00Z",
            "valid_to": "2026-05-21T23:59:59Z"
          },
          "probability_seismic": 0.723575,
          "gps_reliability": 0.5,
          "boost": 0.0
        },
        "T2": {
          "probability": 0.427259,
          "alerts": {
            "0.5pct": false,
            "1.0pct": false,
            "2.0pct": false,
            "5.0pct": false,
            "10.0pct": false
          },
          "validity": {
            "window_days": 2,
            "valid_from": "2026-05-20T00:00:00Z",
            "valid_to": "2026-05-21T23:59:59Z"
          },
          "probability_seismic": 0.427259,
          "gps_reliability": 0.5,
          "boost": 0.0
        },
        "T3": {
          "probability": 0.296707,
          "alerts": {
            "0.5pct": false,
            "1.0pct": false,
            "2.0pct": false,
            "5.0pct": false,
            "10.0pct": false
          },
          "validity": {
            "window_days": 3,
            "valid_from": "2026-05-20T00:00:00Z",
            "valid_to": "2026-05-22T23:59:59Z"
          },
          "probability_seismic": 0.296707,
          "gps_reliability": 0.5,
          "boost": 0.0
        },
        "T4": {
          "probability": 0.242609,
          "alerts": {
            "0.5pct": false,
            "1.0pct": false,
            "2.0pct": false,
            "5.0pct": false,
            "10.0pct": false
          },
          "validity": {
            "window_days": 3,
            "valid_from": "2026-05-20T00:00:00Z",
            "valid_to": "2026-05-22T23:59:59Z"
          },
          "probability_seismic": 0.242609,
          "gps_reliability": 0.5,
          "boost": -0.0
        }
      }
    },
    {
      "zone_id": "Z_20_125",
      "name": "Z_20_125",
      "pop_millions": 0,
      "tiers": {
        "T1": {
          "probability": 0.30398,
          "alerts": {
            "0.5pct": false,
            "1.0pct": false,
            "2.0pct": false,
            "5.0pct": false,
            "10.0pct": false
          },
          "validity": {
            "window_days": 2,
            "valid_from": "2026-05-20T00:00:00Z",
            "valid_to": "2026-05-21T23:59:59Z"
          },
          "probability_seismic": 0.30398,
          "gps_reliability": 0.25,
          "boost": 0.0
        },
        "T2": {
          "probability": 0.045873,
          "alerts": {
            "0.5pct": false,
            "1.0pct": false,
            "2.0pct": false,
            "5.0pct": false,
            "10.0pct": false
          },
          "validity": {
            "window_days": 2,
            "valid_from": "2026-05-20T00:00:00Z",
            "valid_to": "2026-05-21T23:59:59Z"
          },
          "probability_seismic": 0.045873,
          "gps_reliability": 0.25,
          "boost": 0.0
        },
        "T3": {
          "probability": 0.009684,
          "alerts": {
            "0.5pct": false,
            "1.0pct": false,
            "2.0pct": false,
            "5.0pct": false,
            "10.0pct": false
          },
          "validity": {
            "window_days": 3,
            "valid_from": "2026-05-20T00:00:00Z",
            "valid_to": "2026-05-22T23:59:59Z"
          },
          "probability_seismic": 0.009684,
          "gps_reliability": 0.25,
          "boost": -0.0
        },
        "T4": {
          "probability": 0.002404,
          "alerts": {
            "0.5pct": false,
            "1.0pct": false,
            "2.0pct": false,
            "5.0pct": false,
            "10.0pct": false
          },
          "validity": {
            "window_days": 3,
            "valid_from": "2026-05-20T00:00:00Z",
            "valid_to": "2026-05-22T23:59:59Z"
          },
          "probability_seismic": 0.002404,
          "gps_reliability": 0.25,
          "boost": 0.0
        }
      }
    },
    {
      "zone_id": "Z_20_140",
      "name": "Z_20_140",
      "pop_millions": 0,
      "tiers": {
        "T1": {
          "probability": 0.034875,
          "alerts": {
            "0.5pct": false,
            "1.0pct": false,
            "2.0pct": false,
            "5.0pct": false,
            "10.0pct": false
          },
          "validity": {
            "window_days": 2,
            "valid_from": "2026-05-20T00:00:00Z",
            "valid_to": "2026-05-21T23:59:59Z"
          },
          "probability_seismic": 0.034875,
          "gps_reliability": 0.396,
          "boost": -0.0
        },
        "T2": {
          "probability": 0.295771,
          "alerts": {
            "0.5pct": false,
            "1.0pct": false,
            "2.0pct": false,
            "5.0pct": false,
            "10.0pct": false
          },
          "validity": {
            "window_days": 2,
            "valid_from": "2026-05-20T00:00:00Z",
            "valid_to": "2026-05-21T23:59:59Z"
          },
          "probability_seismic": 0.295771,
          "gps_reliability": 0.396,
          "boost": 0.0
        },
        "T3": {
          "probability": 0.386144,
          "alerts": {
            "0.5pct": false,
            "1.0pct": false,
            "2.0pct": false,
            "5.0pct": false,
            "10.0pct": false
          },
          "validity": {
            "window_days": 3,
            "valid_from": "2026-05-20T00:00:00Z",
            "valid_to": "2026-05-22T23:59:59Z"
          },
          "probability_seismic": 0.386144,
          "gps_reliability": 0.396,
          "boost": 0.0
        },
        "T4": {
          "probability": 0.269782,
          "alerts": {
            "0.5pct": false,
            "1.0pct": false,
            "2.0pct": false,
            "5.0pct": false,
            "10.0pct": false
          },
          "validity": {
            "window_days": 3,
            "valid_from": "2026-05-20T00:00:00Z",
            "valid_to": "2026-05-22T23:59:59Z"
          },
          "probability_seismic": 0.269782,
          "gps_reliability": 0.396,
          "boost": 0.0
        }
      }
    },
    {
      "zone_id": "Z_20_145",
      "name": "Z_20_145",
      "pop_millions": 0,
      "tiers": {
        "T1": {
          "probability": 0.037658,
          "alerts": {
            "0.5pct": false,
            "1.0pct": false,
            "2.0pct": false,
            "5.0pct": false,
            "10.0pct": false
          },
          "validity": {
            "window_days": 2,
            "valid_from": "2026-05-20T00:00:00Z",
            "valid_to": "2026-05-21T23:59:59Z"
          }
        },
        "T2": {
          "probability": 0.25803,
          "alerts": {
            "0.5pct": false,
            "1.0pct": false,
            "2.0pct": false,
            "5.0pct": false,
            "10.0pct": false
          },
          "validity": {
            "window_days": 2,
            "valid_from": "2026-05-20T00:00:00Z",
            "valid_to": "2026-05-21T23:59:59Z"
          }
        },
        "T3": {
          "probability": 0.333596,
          "alerts": {
            "0.5pct": false,
            "1.0pct": false,
            "2.0pct": false,
            "5.0pct": false,
            "10.0pct": false
          },
          "validity": {
            "window_days": 3,
            "valid_from": "2026-05-20T00:00:00Z",
            "valid_to": "2026-05-22T23:59:59Z"
          }
        },
        "T4": {
          "probability": 0.309625,
          "alerts": {
            "0.5pct": false,
            "1.0pct": false,
            "2.0pct": false,
            "5.0pct": false,
            "10.0pct": false
          },
          "validity": {
            "window_days": 3,
            "valid_from": "2026-05-20T00:00:00Z",
            "valid_to": "2026-05-22T23:59:59Z"
          }
        }
      }
    },
    {
      "zone_id": "Z_25_120",
      "name": "Z_25_120",
      "pop_millions": 2,
      "tiers": {
        "T1": {
          "probability": 0.186886,
          "alerts": {
            "0.5pct": false,
            "1.0pct": false,
            "2.0pct": false,
            "5.0pct": false,
            "10.0pct": false
          },
          "validity": {
            "window_days": 2,
            "valid_from": "2026-05-20T00:00:00Z",
            "valid_to": "2026-05-21T23:59:59Z"
          },
          "probability_seismic": 0.186886,
          "gps_reliability": 0.896,
          "boost": 0.0
        },
        "T2": {
          "probability": 0.213982,
          "alerts": {
            "0.5pct": false,
            "1.0pct": false,
            "2.0pct": false,
            "5.0pct": false,
            "10.0pct": false
          },
          "validity": {
            "window_days": 2,
            "valid_from": "2026-05-20T00:00:00Z",
            "valid_to": "2026-05-21T23:59:59Z"
          },
          "probability_seismic": 0.213982,
          "gps_reliability": 0.896,
          "boost": 0.0
        },
        "T3": {
          "probability": 0.126005,
          "alerts": {
            "0.5pct": false,
            "1.0pct": false,
            "2.0pct": false,
            "5.0pct": false,
            "10.0pct": false
          },
          "validity": {
            "window_days": 3,
            "valid_from": "2026-05-20T00:00:00Z",
            "valid_to": "2026-05-22T23:59:59Z"
          },
          "probability_seismic": 0.126005,
          "gps_reliability": 0.896,
          "boost": -0.0
        },
        "T4": {
          "probability": 0.118075,
          "alerts": {
            "0.5pct": false,
            "1.0pct": false,
            "2.0pct": false,
            "5.0pct": false,
            "10.0pct": false
          },
          "validity": {
            "window_days": 3,
            "valid_from": "2026-05-20T00:00:00Z",
            "valid_to": "2026-05-22T23:59:59Z"
          },
          "probability_seismic": 0.118075,
          "gps_reliability": 0.896,
          "boost": 0.0
        }
      }
    },
    {
      "zone_id": "Z_25_125",
      "name": "Z_25_125",
      "pop_millions": 0,
      "tiers": {
        "T1": {
          "probability": 0.563873,
          "alerts": {
            "0.5pct": false,
            "1.0pct": false,
            "2.0pct": false,
            "5.0pct": false,
            "10.0pct": false
          },
          "validity": {
            "window_days": 2,
            "valid_from": "2026-05-20T00:00:00Z",
            "valid_to": "2026-05-21T23:59:59Z"
          },
          "probability_seismic": 0.563873,
          "gps_reliability": 0.396,
          "boost": 0.0
        },
        "T2": {
          "probability": 0.258463,
          "alerts": {
            "0.5pct": false,
            "1.0pct": false,
            "2.0pct": false,
            "5.0pct": false,
            "10.0pct": false
          },
          "validity": {
            "window_days": 2,
            "valid_from": "2026-05-20T00:00:00Z",
            "valid_to": "2026-05-21T23:59:59Z"
          },
          "probability_seismic": 0.258463,
          "gps_reliability": 0.396,
          "boost": 0.0
        },
        "T3": {
          "probability": 0.177121,
          "alerts": {
            "0.5pct": false,
            "1.0pct": false,
            "2.0pct": false,
            "5.0pct": false,
            "10.0pct": false
          },
          "validity": {
            "window_days": 3,
            "valid_from": "2026-05-20T00:00:00Z",
            "valid_to": "2026-05-22T23:59:59Z"
          },
          "probability_seismic": 0.177121,
          "gps_reliability": 0.396,
          "boost": -0.0
        },
        "T4": {
          "probability": 0.155611,
          "alerts": {
            "0.5pct": false,
            "1.0pct": false,
            "2.0pct": false,
            "5.0pct": false,
            "10.0pct": false
          },
          "validity": {
            "window_days": 3,
            "valid_from": "2026-05-20T00:00:00Z",
            "valid_to": "2026-05-22T23:59:59Z"
          },
          "probability_seismic": 0.155611,
          "gps_reliability": 0.396,
          "boost": 0.0
        }
      }
    },
    {
      "zone_id": "Z_25_130",
      "name": "Z_25_130",
      "pop_millions": 0,
      "tiers": {
        "T1": {
          "probability": 0.256052,
          "alerts": {
            "0.5pct": false,
            "1.0pct": false,
            "2.0pct": false,
            "5.0pct": false,
            "10.0pct": false
          },
          "validity": {
            "window_days": 2,
            "valid_from": "2026-05-20T00:00:00Z",
            "valid_to": "2026-05-21T23:59:59Z"
          },
          "probability_seismic": 0.256052,
          "gps_reliability": 0.5,
          "boost": 0.0
        },
        "T2": {
          "probability": 0.045019,
          "alerts": {
            "0.5pct": false,
            "1.0pct": false,
            "2.0pct": false,
            "5.0pct": false,
            "10.0pct": false
          },
          "validity": {
            "window_days": 2,
            "valid_from": "2026-05-20T00:00:00Z",
            "valid_to": "2026-05-21T23:59:59Z"
          },
          "probability_seismic": 0.045019,
          "gps_reliability": 0.5,
          "boost": -0.0
        },
        "T3": {
          "probability": 0.011016,
          "alerts": {
            "0.5pct": false,
            "1.0pct": false,
            "2.0pct": false,
            "5.0pct": false,
            "10.0pct": false
          },
          "validity": {
            "window_days": 3,
            "valid_from": "2026-05-20T00:00:00Z",
            "valid_to": "2026-05-22T23:59:59Z"
          },
          "probability_seismic": 0.011016,
          "gps_reliability": 0.5,
          "boost": 0.0
        },
        "T4": {
          "probability": 0.0031,
          "alerts": {
            "0.5pct": false,
            "1.0pct": false,
            "2.0pct": false,
            "5.0pct": false,
            "10.0pct": false
          },
          "validity": {
            "window_days": 3,
            "valid_from": "2026-05-20T00:00:00Z",
            "valid_to": "2026-05-22T23:59:59Z"
          },
          "probability_seismic": 0.0031,
          "gps_reliability": 0.5,
          "boost": 0.0
        }
      }
    },
    {
      "zone_id": "Z_25_135",
      "name": "Z_25_135",
      "pop_millions": 0,
      "tiers": {
        "T1": {
          "probability": 0.075054,
          "alerts": {
            "0.5pct": false,
            "1.0pct": false,
            "2.0pct": false,
            "5.0pct": false,
            "10.0pct": false
          },
          "validity": {
            "window_days": 2,
            "valid_from": "2026-05-20T00:00:00Z",
            "valid_to": "2026-05-21T23:59:59Z"
          }
        },
        "T2": {
          "probability": 0.30288,
          "alerts": {
            "0.5pct": false,
            "1.0pct": false,
            "2.0pct": false,
            "5.0pct": false,
            "10.0pct": false
          },
          "validity": {
            "window_days": 2,
            "valid_from": "2026-05-20T00:00:00Z",
            "valid_to": "2026-05-21T23:59:59Z"
          }
        },
        "T3": {
          "probability": 0.360144,
          "alerts": {
            "0.5pct": false,
            "1.0pct": false,
            "2.0pct": false,
            "5.0pct": false,
            "10.0pct": false
          },
          "validity": {
            "window_days": 3,
            "valid_from": "2026-05-20T00:00:00Z",
            "valid_to": "2026-05-22T23:59:59Z"
          }
        },
        "T4": {
          "probability": 0.340194,
          "alerts": {
            "0.5pct": false,
            "1.0pct": false,
            "2.0pct": false,
            "5.0pct": false,
            "10.0pct": false
          },
          "validity": {
            "window_days": 3,
            "valid_from": "2026-05-20T00:00:00Z",
            "valid_to": "2026-05-22T23:59:59Z"
          }
        }
      }
    },
    {
      "zone_id": "Z_25_140",
      "name": "Z_25_140",
      "pop_millions": 0,
      "tiers": {
        "T1": {
          "probability": 0.463396,
          "alerts": {
            "0.5pct": false,
            "1.0pct": false,
            "2.0pct": false,
            "5.0pct": false,
            "10.0pct": false
          },
          "validity": {
            "window_days": 2,
            "valid_from": "2026-05-20T00:00:00Z",
            "valid_to": "2026-05-21T23:59:59Z"
          },
          "probability_seismic": 0.463396,
          "gps_reliability": 0.5,
          "boost": 0.0
        },
        "T2": {
          "probability": 0.605625,
          "alerts": {
            "0.5pct": false,
            "1.0pct": false,
            "2.0pct": false,
            "5.0pct": false,
            "10.0pct": false
          },
          "validity": {
            "window_days": 2,
            "valid_from": "2026-05-20T00:00:00Z",
            "valid_to": "2026-05-21T23:59:59Z"
          },
          "probability_seismic": 0.605625,
          "gps_reliability": 0.5,
          "boost": 0.0
        },
        "T3": {
          "probability": 0.571612,
          "alerts": {
            "0.5pct": false,
            "1.0pct": false,
            "2.0pct": false,
            "5.0pct": false,
            "10.0pct": false
          },
          "validity": {
            "window_days": 3,
            "valid_from": "2026-05-20T00:00:00Z",
            "valid_to": "2026-05-22T23:59:59Z"
          },
          "probability_seismic": 0.571612,
          "gps_reliability": 0.5,
          "boost": 0.0
        },
        "T4": {
          "probability": 0.512623,
          "alerts": {
            "0.5pct": false,
            "1.0pct": false,
            "2.0pct": false,
            "5.0pct": false,
            "10.0pct": false
          },
          "validity": {
            "window_days": 3,
            "valid_from": "2026-05-20T00:00:00Z",
            "valid_to": "2026-05-22T23:59:59Z"
          },
          "probability_seismic": 0.512623,
          "gps_reliability": 0.5,
          "boost": 0.0
        }
      }
    },
    {
      "zone_id": "Z_30_125",
      "name": "Z_30_125",
      "pop_millions": 0,
      "tiers": {
        "T1": {
          "probability": 0.401229,
          "alerts": {
            "0.5pct": false,
            "1.0pct": false,
            "2.0pct": false,
            "5.0pct": false,
            "10.0pct": false
          },
          "validity": {
            "window_days": 2,
            "valid_from": "2026-05-20T00:00:00Z",
            "valid_to": "2026-05-21T23:59:59Z"
          },
          "probability_seismic": 0.401229,
          "gps_reliability": 1.0,
          "boost": 0.0
        },
        "T2": {
          "probability": 0.409898,
          "alerts": {
            "0.5pct": false,
            "1.0pct": false,
            "2.0pct": false,
            "5.0pct": false,
            "10.0pct": false
          },
          "validity": {
            "window_days": 2,
            "valid_from": "2026-05-20T00:00:00Z",
            "valid_to": "2026-05-21T23:59:59Z"
          },
          "probability_seismic": 0.409898,
          "gps_reliability": 1.0,
          "boost": 0.0
        },
        "T3": {
          "probability": 0.362398,
          "alerts": {
            "0.5pct": false,
            "1.0pct": false,
            "2.0pct": false,
            "5.0pct": false,
            "10.0pct": false
          },
          "validity": {
            "window_days": 3,
            "valid_from": "2026-05-20T00:00:00Z",
            "valid_to": "2026-05-22T23:59:59Z"
          },
          "probability_seismic": 0.362398,
          "gps_reliability": 1.0,
          "boost": -0.0
        },
        "T4": {
          "probability": 0.333527,
          "alerts": {
            "0.5pct": false,
            "1.0pct": false,
            "2.0pct": false,
            "5.0pct": false,
            "10.0pct": false
          },
          "validity": {
            "window_days": 3,
            "valid_from": "2026-05-20T00:00:00Z",
            "valid_to": "2026-05-22T23:59:59Z"
          },
          "probability_seismic": 0.333527,
          "gps_reliability": 1.0,
          "boost": 0.0
        }
      }
    },
    {
      "zone_id": "Z_30_130",
      "name": "Kyushu-South",
      "pop_millions": 13,
      "tiers": {
        "T1": {
          "probability": 0.539766,
          "alerts": {
            "0.5pct": false,
            "1.0pct": false,
            "2.0pct": false,
            "5.0pct": false,
            "10.0pct": false
          },
          "validity": {
            "window_days": 2,
            "valid_from": "2026-05-20T00:00:00Z",
            "valid_to": "2026-05-21T23:59:59Z"
          },
          "probability_seismic": 0.539766,
          "gps_reliability": 0.58,
          "boost": 0.0
        },
        "T2": {
          "probability": 0.244687,
          "alerts": {
            "0.5pct": false,
            "1.0pct": false,
            "2.0pct": false,
            "5.0pct": false,
            "10.0pct": false
          },
          "validity": {
            "window_days": 2,
            "valid_from": "2026-05-20T00:00:00Z",
            "valid_to": "2026-05-21T23:59:59Z"
          },
          "probability_seismic": 0.244687,
          "gps_reliability": 0.58,
          "boost": 0.0
        },
        "T3": {
          "probability": 0.142803,
          "alerts": {
            "0.5pct": false,
            "1.0pct": false,
            "2.0pct": false,
            "5.0pct": false,
            "10.0pct": false
          },
          "validity": {
            "window_days": 3,
            "valid_from": "2026-05-20T00:00:00Z",
            "valid_to": "2026-05-22T23:59:59Z"
          },
          "probability_seismic": 0.142803,
          "gps_reliability": 0.58,
          "boost": 0.0
        },
        "T4": {
          "probability": 0.116594,
          "alerts": {
            "0.5pct": false,
            "1.0pct": false,
            "2.0pct": false,
            "5.0pct": false,
            "10.0pct": false
          },
          "validity": {
            "window_days": 3,
            "valid_from": "2026-05-20T00:00:00Z",
            "valid_to": "2026-05-22T23:59:59Z"
          },
          "probability_seismic": 0.116594,
          "gps_reliability": 0.58,
          "boost": -0.0
        }
      }
    },
    {
      "zone_id": "Z_30_135",
      "name": "Kyushu-North",
      "pop_millions": 4,
      "tiers": {
        "T1": {
          "probability": 0.507869,
          "alerts": {
            "0.5pct": false,
            "1.0pct": false,
            "2.0pct": false,
            "5.0pct": false,
            "10.0pct": false
          },
          "validity": {
            "window_days": 2,
            "valid_from": "2026-05-20T00:00:00Z",
            "valid_to": "2026-05-21T23:59:59Z"
          },
          "probability_seismic": 0.507869,
          "gps_reliability": 0.25,
          "boost": 0.0
        },
        "T2": {
          "probability": 0.310339,
          "alerts": {
            "0.5pct": false,
            "1.0pct": false,
            "2.0pct": false,
            "5.0pct": false,
            "10.0pct": false
          },
          "validity": {
            "window_days": 2,
            "valid_from": "2026-05-20T00:00:00Z",
            "valid_to": "2026-05-21T23:59:59Z"
          },
          "probability_seismic": 0.310339,
          "gps_reliability": 0.25,
          "boost": 0.0
        },
        "T3": {
          "probability": 0.257231,
          "alerts": {
            "0.5pct": false,
            "1.0pct": false,
            "2.0pct": false,
            "5.0pct": false,
            "10.0pct": false
          },
          "validity": {
            "window_days": 3,
            "valid_from": "2026-05-20T00:00:00Z",
            "valid_to": "2026-05-22T23:59:59Z"
          },
          "probability_seismic": 0.257231,
          "gps_reliability": 0.25,
          "boost": 0.0
        },
        "T4": {
          "probability": 0.230648,
          "alerts": {
            "0.5pct": false,
            "1.0pct": false,
            "2.0pct": false,
            "5.0pct": false,
            "10.0pct": false
          },
          "validity": {
            "window_days": 3,
            "valid_from": "2026-05-20T00:00:00Z",
            "valid_to": "2026-05-22T23:59:59Z"
          },
          "probability_seismic": 0.230648,
          "gps_reliability": 0.25,
          "boost": 0.0
        }
      }
    },
    {
      "zone_id": "Z_30_140",
      "name": "Z_30_140",
      "pop_millions": 0,
      "tiers": {
        "T1": {
          "probability": 0.557043,
          "alerts": {
            "0.5pct": false,
            "1.0pct": false,
            "2.0pct": false,
            "5.0pct": false,
            "10.0pct": false
          },
          "validity": {
            "window_days": 2,
            "valid_from": "2026-05-20T00:00:00Z",
            "valid_to": "2026-05-21T23:59:59Z"
          }
        },
        "T2": {
          "probability": 0.222658,
          "alerts": {
            "0.5pct": false,
            "1.0pct": false,
            "2.0pct": false,
            "5.0pct": false,
            "10.0pct": false
          },
          "validity": {
            "window_days": 2,
            "valid_from": "2026-05-20T00:00:00Z",
            "valid_to": "2026-05-21T23:59:59Z"
          }
        },
        "T3": {
          "probability": 0.114734,
          "alerts": {
            "0.5pct": false,
            "1.0pct": false,
            "2.0pct": false,
            "5.0pct": false,
            "10.0pct": false
          },
          "validity": {
            "window_days": 3,
            "valid_from": "2026-05-20T00:00:00Z",
            "valid_to": "2026-05-22T23:59:59Z"
          }
        },
        "T4": {
          "probability": 0.091907,
          "alerts": {
            "0.5pct": false,
            "1.0pct": false,
            "2.0pct": false,
            "5.0pct": false,
            "10.0pct": false
          },
          "validity": {
            "window_days": 3,
            "valid_from": "2026-05-20T00:00:00Z",
            "valid_to": "2026-05-22T23:59:59Z"
          }
        }
      }
    },
    {
      "zone_id": "Z_35_130",
      "name": "Shikoku",
      "pop_millions": 8,
      "tiers": {
        "T1": {
          "probability": 0.32252,
          "alerts": {
            "0.5pct": false,
            "1.0pct": false,
            "2.0pct": false,
            "5.0pct": false,
            "10.0pct": false
          },
          "validity": {
            "window_days": 2,
            "valid_from": "2026-05-20T00:00:00Z",
            "valid_to": "2026-05-21T23:59:59Z"
          },
          "probability_seismic": 0.32252,
          "gps_reliability": 0.25,
          "boost": 0.0
        },
        "T2": {
          "probability": 0.074153,
          "alerts": {
            "0.5pct": false,
            "1.0pct": false,
            "2.0pct": false,
            "5.0pct": false,
            "10.0pct": false
          },
          "validity": {
            "window_days": 2,
            "valid_from": "2026-05-20T00:00:00Z",
            "valid_to": "2026-05-21T23:59:59Z"
          },
          "probability_seismic": 0.074153,
          "gps_reliability": 0.25,
          "boost": 0.0
        },
        "T3": {
          "probability": 0.015807,
          "alerts": {
            "0.5pct": false,
            "1.0pct": false,
            "2.0pct": false,
            "5.0pct": false,
            "10.0pct": false
          },
          "validity": {
            "window_days": 3,
            "valid_from": "2026-05-20T00:00:00Z",
            "valid_to": "2026-05-22T23:59:59Z"
          },
          "probability_seismic": 0.015807,
          "gps_reliability": 0.25,
          "boost": 0.0
        },
        "T4": {
          "probability": 0.007904,
          "alerts": {
            "0.5pct": false,
            "1.0pct": false,
            "2.0pct": false,
            "5.0pct": false,
            "10.0pct": false
          },
          "validity": {
            "window_days": 3,
            "valid_from": "2026-05-20T00:00:00Z",
            "valid_to": "2026-05-22T23:59:59Z"
          },
          "probability_seismic": 0.007904,
          "gps_reliability": 0.25,
          "boost": 0.0
        }
      }
    },
    {
      "zone_id": "Z_35_135",
      "name": "Osaka-Kobe",
      "pop_millions": 60,
      "tiers": {
        "T1": {
          "probability": 0.617229,
          "alerts": {
            "0.5pct": false,
            "1.0pct": false,
            "2.0pct": false,
            "5.0pct": false,
            "10.0pct": false
          },
          "validity": {
            "window_days": 2,
            "valid_from": "2026-05-20T00:00:00Z",
            "valid_to": "2026-05-21T23:59:59Z"
          },
          "probability_seismic": 0.617229,
          "gps_reliability": 0.25,
          "boost": 0.0
        },
        "T2": {
          "probability": 0.258679,
          "alerts": {
            "0.5pct": false,
            "1.0pct": false,
            "2.0pct": false,
            "5.0pct": false,
            "10.0pct": false
          },
          "validity": {
            "window_days": 2,
            "valid_from": "2026-05-20T00:00:00Z",
            "valid_to": "2026-05-21T23:59:59Z"
          },
          "probability_seismic": 0.258679,
          "gps_reliability": 0.25,
          "boost": 0.0
        },
        "T3": {
          "probability": 0.170111,
          "alerts": {
            "0.5pct": false,
            "1.0pct": false,
            "2.0pct": false,
            "5.0pct": false,
            "10.0pct": false
          },
          "validity": {
            "window_days": 3,
            "valid_from": "2026-05-20T00:00:00Z",
            "valid_to": "2026-05-22T23:59:59Z"
          },
          "probability_seismic": 0.170111,
          "gps_reliability": 0.25,
          "boost": 0.0
        },
        "T4": {
          "probability": 0.138806,
          "alerts": {
            "0.5pct": false,
            "1.0pct": false,
            "2.0pct": false,
            "5.0pct": false,
            "10.0pct": false
          },
          "validity": {
            "window_days": 3,
            "valid_from": "2026-05-20T00:00:00Z",
            "valid_to": "2026-05-22T23:59:59Z"
          },
          "probability_seismic": 0.138806,
          "gps_reliability": 0.25,
          "boost": 0.0
        }
      }
    },
    {
      "zone_id": "Z_35_140",
      "name": "Tokyo-Kanto",
      "pop_millions": 39,
      "tiers": {
        "T1": {
          "probability": 0.941577,
          "alerts": {
            "0.5pct": false,
            "1.0pct": false,
            "2.0pct": false,
            "5.0pct": false,
            "10.0pct": false
          },
          "validity": {
            "window_days": 2,
            "valid_from": "2026-05-20T00:00:00Z",
            "valid_to": "2026-05-21T23:59:59Z"
          },
          "probability_seismic": 0.941577,
          "gps_reliability": 0.396,
          "boost": 0.0
        },
        "T2": {
          "probability": 0.566226,
          "alerts": {
            "0.5pct": false,
            "1.0pct": false,
            "2.0pct": false,
            "5.0pct": false,
            "10.0pct": false
          },
          "validity": {
            "window_days": 2,
            "valid_from": "2026-05-20T00:00:00Z",
            "valid_to": "2026-05-21T23:59:59Z"
          },
          "probability_seismic": 0.566226,
          "gps_reliability": 0.396,
          "boost": 0.0
        },
        "T3": {
          "probability": 0.5942,
          "alerts": {
            "0.5pct": false,
            "1.0pct": false,
            "2.0pct": false,
            "5.0pct": false,
            "10.0pct": false
          },
          "validity": {
            "window_days": 3,
            "valid_from": "2026-05-20T00:00:00Z",
            "valid_to": "2026-05-22T23:59:59Z"
          },
          "probability_seismic": 0.5942,
          "gps_reliability": 0.396,
          "boost": 0.0
        },
        "T4": {
          "probability": 0.561706,
          "alerts": {
            "0.5pct": false,
            "1.0pct": false,
            "2.0pct": false,
            "5.0pct": false,
            "10.0pct": false
          },
          "validity": {
            "window_days": 3,
            "valid_from": "2026-05-20T00:00:00Z",
            "valid_to": "2026-05-22T23:59:59Z"
          },
          "probability_seismic": 0.561706,
          "gps_reliability": 0.396,
          "boost": 0.0
        }
      }
    },
    {
      "zone_id": "Z_40_130",
      "name": "Z_40_130",
      "pop_millions": 0,
      "tiers": {
        "T1": {
          "probability": 0.036695,
          "alerts": {
            "0.5pct": false,
            "1.0pct": false,
            "2.0pct": false,
            "5.0pct": false,
            "10.0pct": false
          },
          "validity": {
            "window_days": 2,
            "valid_from": "2026-05-20T00:00:00Z",
            "valid_to": "2026-05-21T23:59:59Z"
          },
          "probability_seismic": 0.036695,
          "gps_reliability": 0.25,
          "boost": -0.0
        },
        "T2": {
          "probability": 0.256302,
          "alerts": {
            "0.5pct": false,
            "1.0pct": false,
            "2.0pct": false,
            "5.0pct": false,
            "10.0pct": false
          },
          "validity": {
            "window_days": 2,
            "valid_from": "2026-05-20T00:00:00Z",
            "valid_to": "2026-05-21T23:59:59Z"
          },
          "probability_seismic": 0.256302,
          "gps_reliability": 0.25,
          "boost": 0.0
        },
        "T3": {
          "probability": 0.332233,
          "alerts": {
            "0.5pct": false,
            "1.0pct": false,
            "2.0pct": false,
            "5.0pct": false,
            "10.0pct": false
          },
          "validity": {
            "window_days": 3,
            "valid_from": "2026-05-20T00:00:00Z",
            "valid_to": "2026-05-22T23:59:59Z"
          },
          "probability_seismic": 0.332233,
          "gps_reliability": 0.25,
          "boost": 0.0
        },
        "T4": {
          "probability": 0.307897,
          "alerts": {
            "0.5pct": false,
            "1.0pct": false,
            "2.0pct": false,
            "5.0pct": false,
            "10.0pct": false
          },
          "validity": {
            "window_days": 3,
            "valid_from": "2026-05-20T00:00:00Z",
            "valid_to": "2026-05-22T23:59:59Z"
          },
          "probability_seismic": 0.307897,
          "gps_reliability": 0.25,
          "boost": 0.0
        }
      }
    },
    {
      "zone_id": "Z_40_135",
      "name": "Niigata",
      "pop_millions": 8,
      "tiers": {
        "T1": {
          "probability": 0.249697,
          "alerts": {
            "0.5pct": false,
            "1.0pct": false,
            "2.0pct": false,
            "5.0pct": false,
            "10.0pct": false
          },
          "validity": {
            "window_days": 2,
            "valid_from": "2026-05-20T00:00:00Z",
            "valid_to": "2026-05-21T23:59:59Z"
          },
          "probability_seismic": 0.249697,
          "gps_reliability": 0.25,
          "boost": 0.0
        },
        "T2": {
          "probability": 0.263702,
          "alerts": {
            "0.5pct": false,
            "1.0pct": false,
            "2.0pct": false,
            "5.0pct": false,
            "10.0pct": false
          },
          "validity": {
            "window_days": 2,
            "valid_from": "2026-05-20T00:00:00Z",
            "valid_to": "2026-05-21T23:59:59Z"
          },
          "probability_seismic": 0.263702,
          "gps_reliability": 0.25,
          "boost": 0.0
        },
        "T3": {
          "probability": 0.228922,
          "alerts": {
            "0.5pct": false,
            "1.0pct": false,
            "2.0pct": false,
            "5.0pct": false,
            "10.0pct": false
          },
          "validity": {
            "window_days": 3,
            "valid_from": "2026-05-20T00:00:00Z",
            "valid_to": "2026-05-22T23:59:59Z"
          },
          "probability_seismic": 0.228922,
          "gps_reliability": 0.25,
          "boost": 0.0
        },
        "T4": {
          "probability": 0.210944,
          "alerts": {
            "0.5pct": false,
            "1.0pct": false,
            "2.0pct": false,
            "5.0pct": false,
            "10.0pct": false
          },
          "validity": {
            "window_days": 3,
            "valid_from": "2026-05-20T00:00:00Z",
            "valid_to": "2026-05-22T23:59:59Z"
          },
          "probability_seismic": 0.210944,
          "gps_reliability": 0.25,
          "boost": 0.0
        }
      }
    },
    {
      "zone_id": "Z_40_140",
      "name": "Hokkaido-S",
      "pop_millions": 4,
      "tiers": {
        "T1": {
          "probability": 0.854645,
          "alerts": {
            "0.5pct": false,
            "1.0pct": false,
            "2.0pct": false,
            "5.0pct": false,
            "10.0pct": false
          },
          "validity": {
            "window_days": 2,
            "valid_from": "2026-05-20T00:00:00Z",
            "valid_to": "2026-05-21T23:59:59Z"
          },
          "probability_seismic": 0.854645,
          "gps_reliability": 0.58,
          "boost": 0.0
        },
        "T2": {
          "probability": 0.505898,
          "alerts": {
            "0.5pct": false,
            "1.0pct": false,
            "2.0pct": false,
            "5.0pct": false,
            "10.0pct": false
          },
          "validity": {
            "window_days": 2,
            "valid_from": "2026-05-20T00:00:00Z",
            "valid_to": "2026-05-21T23:59:59Z"
          },
          "probability_seismic": 0.505898,
          "gps_reliability": 0.58,
          "boost": 0.0
        },
        "T3": {
          "probability": 0.478728,
          "alerts": {
            "0.5pct": false,
            "1.0pct": false,
            "2.0pct": false,
            "5.0pct": false,
            "10.0pct": false
          },
          "validity": {
            "window_days": 3,
            "valid_from": "2026-05-20T00:00:00Z",
            "valid_to": "2026-05-22T23:59:59Z"
          },
          "probability_seismic": 0.478728,
          "gps_reliability": 0.58,
          "boost": 0.0
        },
        "T4": {
          "probability": 0.438905,
          "alerts": {
            "0.5pct": false,
            "1.0pct": false,
            "2.0pct": false,
            "5.0pct": false,
            "10.0pct": false
          },
          "validity": {
            "window_days": 3,
            "valid_from": "2026-05-20T00:00:00Z",
            "valid_to": "2026-05-22T23:59:59Z"
          },
          "probability_seismic": 0.438905,
          "gps_reliability": 0.58,
          "boost": 0.0
        }
      }
    },
    {
      "zone_id": "Z_40_145",
      "name": "Hokkaido-E",
      "pop_millions": 5,
      "tiers": {
        "T1": {
          "probability": 0.518427,
          "alerts": {
            "0.5pct": false,
            "1.0pct": false,
            "2.0pct": false,
            "5.0pct": false,
            "10.0pct": false
          },
          "validity": {
            "window_days": 2,
            "valid_from": "2026-05-20T00:00:00Z",
            "valid_to": "2026-05-21T23:59:59Z"
          },
          "probability_seismic": 0.518427,
          "gps_reliability": 0.25,
          "boost": 0.0
        },
        "T2": {
          "probability": 0.263295,
          "alerts": {
            "0.5pct": false,
            "1.0pct": false,
            "2.0pct": false,
            "5.0pct": false,
            "10.0pct": false
          },
          "validity": {
            "window_days": 2,
            "valid_from": "2026-05-20T00:00:00Z",
            "valid_to": "2026-05-21T23:59:59Z"
          },
          "probability_seismic": 0.263295,
          "gps_reliability": 0.25,
          "boost": 0.0
        },
        "T3": {
          "probability": 0.148508,
          "alerts": {
            "0.5pct": false,
            "1.0pct": false,
            "2.0pct": false,
            "5.0pct": false,
            "10.0pct": false
          },
          "validity": {
            "window_days": 3,
            "valid_from": "2026-05-20T00:00:00Z",
            "valid_to": "2026-05-22T23:59:59Z"
          },
          "probability_seismic": 0.148508,
          "gps_reliability": 0.25,
          "boost": 0.0
        },
        "T4": {
          "probability": 0.107808,
          "alerts": {
            "0.5pct": false,
            "1.0pct": false,
            "2.0pct": false,
            "5.0pct": false,
            "10.0pct": false
          },
          "validity": {
            "window_days": 3,
            "valid_from": "2026-05-20T00:00:00Z",
            "valid_to": "2026-05-22T23:59:59Z"
          },
          "probability_seismic": 0.107808,
          "gps_reliability": 0.25,
          "boost": 0.0
        }
      }
    },
    {
      "zone_id": "Z_40_150",
      "name": "Z_40_150",
      "pop_millions": 0,
      "tiers": {
        "T1": {
          "probability": 0.036856,
          "alerts": {
            "0.5pct": false,
            "1.0pct": false,
            "2.0pct": false,
            "5.0pct": false,
            "10.0pct": false
          },
          "validity": {
            "window_days": 2,
            "valid_from": "2026-05-20T00:00:00Z",
            "valid_to": "2026-05-21T23:59:59Z"
          }
        },
        "T2": {
          "probability": 0.256595,
          "alerts": {
            "0.5pct": false,
            "1.0pct": false,
            "2.0pct": false,
            "5.0pct": false,
            "10.0pct": false
          },
          "validity": {
            "window_days": 2,
            "valid_from": "2026-05-20T00:00:00Z",
            "valid_to": "2026-05-21T23:59:59Z"
          }
        },
        "T3": {
          "probability": 0.332448,
          "alerts": {
            "0.5pct": false,
            "1.0pct": false,
            "2.0pct": false,
            "5.0pct": false,
            "10.0pct": false
          },
          "validity": {
            "window_days": 3,
            "valid_from": "2026-05-20T00:00:00Z",
            "valid_to": "2026-05-22T23:59:59Z"
          }
        },
        "T4": {
          "probability": 0.308152,
          "alerts": {
            "0.5pct": false,
            "1.0pct": false,
            "2.0pct": false,
            "5.0pct": false,
            "10.0pct": false
          },
          "validity": {
            "window_days": 3,
            "valid_from": "2026-05-20T00:00:00Z",
            "valid_to": "2026-05-22T23:59:59Z"
          }
        }
      }
    },
    {
      "zone_id": "Z_45_140",
      "name": "Z_45_140",
      "pop_millions": 0,
      "tiers": {
        "T1": {
          "probability": 0.115326,
          "alerts": {
            "0.5pct": false,
            "1.0pct": false,
            "2.0pct": false,
            "5.0pct": false,
            "10.0pct": false
          },
          "validity": {
            "window_days": 2,
            "valid_from": "2026-05-20T00:00:00Z",
            "valid_to": "2026-05-21T23:59:59Z"
          },
          "probability_seismic": 0.115326,
          "gps_reliability": 0.25,
          "boost": 0.0
        },
        "T2": {
          "probability": 0.352791,
          "alerts": {
            "0.5pct": false,
            "1.0pct": false,
            "2.0pct": false,
            "5.0pct": false,
            "10.0pct": false
          },
          "validity": {
            "window_days": 2,
            "valid_from": "2026-05-20T00:00:00Z",
            "valid_to": "2026-05-21T23:59:59Z"
          },
          "probability_seismic": 0.352791,
          "gps_reliability": 0.25,
          "boost": 0.0
        },
        "T3": {
          "probability": 0.395989,
          "alerts": {
            "0.5pct": false,
            "1.0pct": false,
            "2.0pct": false,
            "5.0pct": false,
            "10.0pct": true
          },
          "validity": {
            "window_days": 3,
            "valid_from": "2026-05-20T00:00:00Z",
            "valid_to": "2026-05-22T23:59:59Z"
          },
          "probability_seismic": 0.395989,
          "gps_reliability": 0.25,
          "boost": 0.0
        },
        "T4": {
          "probability": 0.324089,
          "alerts": {
            "0.5pct": false,
            "1.0pct": false,
            "2.0pct": false,
            "5.0pct": false,
            "10.0pct": false
          },
          "validity": {
            "window_days": 3,
            "valid_from": "2026-05-20T00:00:00Z",
            "valid_to": "2026-05-22T23:59:59Z"
          },
          "probability_seismic": 0.324089,
          "gps_reliability": 0.25,
          "boost": 0.0
        }
      }
    },
    {
      "zone_id": "Z_45_145",
      "name": "Kuril-South",
      "pop_millions": 5,
      "tiers": {
        "T1": {
          "probability": 0.049816,
          "alerts": {
            "0.5pct": false,
            "1.0pct": false,
            "2.0pct": false,
            "5.0pct": false,
            "10.0pct": false
          },
          "validity": {
            "window_days": 2,
            "valid_from": "2026-05-20T00:00:00Z",
            "valid_to": "2026-05-21T23:59:59Z"
          },
          "probability_seismic": 0.049816,
          "gps_reliability": 0.25,
          "boost": 0.0
        },
        "T2": {
          "probability": 0.273853,
          "alerts": {
            "0.5pct": false,
            "1.0pct": false,
            "2.0pct": false,
            "5.0pct": false,
            "10.0pct": false
          },
          "validity": {
            "window_days": 2,
            "valid_from": "2026-05-20T00:00:00Z",
            "valid_to": "2026-05-21T23:59:59Z"
          },
          "probability_seismic": 0.273853,
          "gps_reliability": 0.25,
          "boost": 0.0
        },
        "T3": {
          "probability": 0.344406,
          "alerts": {
            "0.5pct": false,
            "1.0pct": false,
            "2.0pct": false,
            "5.0pct": false,
            "10.0pct": false
          },
          "validity": {
            "window_days": 3,
            "valid_from": "2026-05-20T00:00:00Z",
            "valid_to": "2026-05-22T23:59:59Z"
          },
          "probability_seismic": 0.344406,
          "gps_reliability": 0.25,
          "boost": 0.0
        },
        "T4": {
          "probability": 0.327932,
          "alerts": {
            "0.5pct": false,
            "1.0pct": false,
            "2.0pct": false,
            "5.0pct": false,
            "10.0pct": false
          },
          "validity": {
            "window_days": 3,
            "valid_from": "2026-05-20T00:00:00Z",
            "valid_to": "2026-05-22T23:59:59Z"
          },
          "probability_seismic": 0.327932,
          "gps_reliability": 0.25,
          "boost": 0.0
        }
      }
    },
    {
      "zone_id": "Z_45_150",
      "name": "Z_45_150",
      "pop_millions": 0,
      "tiers": {
        "T1": {
          "probability": 0.100546,
          "alerts": {
            "0.5pct": false,
            "1.0pct": false,
            "2.0pct": false,
            "5.0pct": false,
            "10.0pct": false
          },
          "validity": {
            "window_days": 2,
            "valid_from": "2026-05-20T00:00:00Z",
            "valid_to": "2026-05-21T23:59:59Z"
          }
        },
        "T2": {
          "probability": 0.329385,
          "alerts": {
            "0.5pct": false,
            "1.0pct": false,
            "2.0pct": false,
            "5.0pct": false,
            "10.0pct": false
          },
          "validity": {
            "window_days": 2,
            "valid_from": "2026-05-20T00:00:00Z",
            "valid_to": "2026-05-21T23:59:59Z"
          }
        },
        "T3": {
          "probability": 0.37573,
          "alerts": {
            "0.5pct": false,
            "1.0pct": false,
            "2.0pct": false,
            "5.0pct": false,
            "10.0pct": false
          },
          "validity": {
            "window_days": 3,
            "valid_from": "2026-05-20T00:00:00Z",
            "valid_to": "2026-05-22T23:59:59Z"
          }
        },
        "T4": {
          "probability": 0.349494,
          "alerts": {
            "0.5pct": false,
            "1.0pct": false,
            "2.0pct": false,
            "5.0pct": false,
            "10.0pct": false
          },
          "validity": {
            "window_days": 3,
            "valid_from": "2026-05-20T00:00:00Z",
            "valid_to": "2026-05-22T23:59:59Z"
          }
        }
      }
    },
    {
      "zone_id": "Z_45_155",
      "name": "Z_45_155",
      "pop_millions": 0,
      "tiers": {
        "T1": {
          "probability": 0.03669,
          "alerts": {
            "0.5pct": false,
            "1.0pct": false,
            "2.0pct": false,
            "5.0pct": false,
            "10.0pct": false
          },
          "validity": {
            "window_days": 2,
            "valid_from": "2026-05-20T00:00:00Z",
            "valid_to": "2026-05-21T23:59:59Z"
          }
        },
        "T2": {
          "probability": 0.256294,
          "alerts": {
            "0.5pct": false,
            "1.0pct": false,
            "2.0pct": false,
            "5.0pct": false,
            "10.0pct": false
          },
          "validity": {
            "window_days": 2,
            "valid_from": "2026-05-20T00:00:00Z",
            "valid_to": "2026-05-21T23:59:59Z"
          }
        },
        "T3": {
          "probability": 0.332203,
          "alerts": {
            "0.5pct": false,
            "1.0pct": false,
            "2.0pct": false,
            "5.0pct": false,
            "10.0pct": false
          },
          "validity": {
            "window_days": 3,
            "valid_from": "2026-05-20T00:00:00Z",
            "valid_to": "2026-05-22T23:59:59Z"
          }
        },
        "T4": {
          "probability": 0.307833,
          "alerts": {
            "0.5pct": false,
            "1.0pct": false,
            "2.0pct": false,
            "5.0pct": false,
            "10.0pct": false
          },
          "validity": {
            "window_days": 3,
            "valid_from": "2026-05-20T00:00:00Z",
            "valid_to": "2026-05-22T23:59:59Z"
          }
        }
      }
    },
    {
      "zone_id": "Z_50_150",
      "name": "Z_50_150",
      "pop_millions": 0,
      "tiers": {
        "T1": {
          "probability": 0.036444,
          "alerts": {
            "0.5pct": false,
            "1.0pct": false,
            "2.0pct": false,
            "5.0pct": false,
            "10.0pct": false
          },
          "validity": {
            "window_days": 2,
            "valid_from": "2026-05-20T00:00:00Z",
            "valid_to": "2026-05-21T23:59:59Z"
          }
        },
        "T2": {
          "probability": 0.255846,
          "alerts": {
            "0.5pct": false,
            "1.0pct": false,
            "2.0pct": false,
            "5.0pct": false,
            "10.0pct": false
          },
          "validity": {
            "window_days": 2,
            "valid_from": "2026-05-20T00:00:00Z",
            "valid_to": "2026-05-21T23:59:59Z"
          }
        },
        "T3": {
          "probability": 0.331851,
          "alerts": {
            "0.5pct": false,
            "1.0pct": false,
            "2.0pct": false,
            "5.0pct": false,
            "10.0pct": false
          },
          "validity": {
            "window_days": 3,
            "valid_from": "2026-05-20T00:00:00Z",
            "valid_to": "2026-05-22T23:59:59Z"
          }
        },
        "T4": {
          "probability": 0.307388,
          "alerts": {
            "0.5pct": false,
            "1.0pct": false,
            "2.0pct": false,
            "5.0pct": false,
            "10.0pct": false
          },
          "validity": {
            "window_days": 3,
            "valid_from": "2026-05-20T00:00:00Z",
            "valid_to": "2026-05-22T23:59:59Z"
          }
        }
      }
    },
    {
      "zone_id": "Z_50_155",
      "name": "Z_50_155",
      "pop_millions": 0,
      "tiers": {
        "T1": {
          "probability": 0.036484,
          "alerts": {
            "0.5pct": false,
            "1.0pct": false,
            "2.0pct": false,
            "5.0pct": false,
            "10.0pct": false
          },
          "validity": {
            "window_days": 2,
            "valid_from": "2026-05-20T00:00:00Z",
            "valid_to": "2026-05-21T23:59:59Z"
          },
          "probability_seismic": 0.036484,
          "gps_reliability": 0.25,
          "boost": -0.0
        },
        "T2": {
          "probability": 0.25592,
          "alerts": {
            "0.5pct": false,
            "1.0pct": false,
            "2.0pct": false,
            "5.0pct": false,
            "10.0pct": false
          },
          "validity": {
            "window_days": 2,
            "valid_from": "2026-05-20T00:00:00Z",
            "valid_to": "2026-05-21T23:59:59Z"
          },
          "probability_seismic": 0.25592,
          "gps_reliability": 0.25,
          "boost": 0.0
        },
        "T3": {
          "probability": 0.331905,
          "alerts": {
            "0.5pct": false,
            "1.0pct": false,
            "2.0pct": false,
            "5.0pct": false,
            "10.0pct": false
          },
          "validity": {
            "window_days": 3,
            "valid_from": "2026-05-20T00:00:00Z",
            "valid_to": "2026-05-22T23:59:59Z"
          },
          "probability_seismic": 0.331905,
          "gps_reliability": 0.25,
          "boost": 0.0
        },
        "T4": {
          "probability": 0.307452,
          "alerts": {
            "0.5pct": false,
            "1.0pct": false,
            "2.0pct": false,
            "5.0pct": false,
            "10.0pct": false
          },
          "validity": {
            "window_days": 3,
            "valid_from": "2026-05-20T00:00:00Z",
            "valid_to": "2026-05-22T23:59:59Z"
          },
          "probability_seismic": 0.307452,
          "gps_reliability": 0.25,
          "boost": 0.0
        }
      }
    }
  ],
  "summary": {
    "total_zones": 29,
    "alerts_by_tier": {
      "T1": 0,
      "T2": 0,
      "T3": 0,
      "T4": 0
    }
  }
}